botcity_aux/__init__.py
botcity_aux/bot_runner.py
botcity_aux/logger_config.py
botcity_aux/telegram_plugin.py
botcity_rpa_template-0.1.1.dist-info/LICENSE
botcity_rpa_template-0.1.1.dist-info/METADATA
botcity_rpa_template-0.1.1.dist-info/WHEEL
botcity_rpa_template-0.1.1.dist-info/entry_points.txt
botcity_rpa_template-0.1.1.dist-info/top_level.txt
botcity_rpa_template-0.1.1.dist-info/RECORD
