Metadata-Version: 2.1
Name: botcity-rpa-template
Version: 0.1.1
Summary: My bot project description
Home-page: https://github.com/jpzinn654/my-package
Author: Your Name
Author-email: your_email@example.com
Classifier: Programming Language :: Python :: 3
Classifier: License :: OSI Approved :: MIT License
Classifier: Operating System :: OS Independent
License-File: LICENSE
Requires-Dist: some_dependency
